Time_Frequency_Analysis/NSGT_CQT.py
Time_Frequency_Analysis/NSGT_custom.py
Time_Frequency_Analysis/SCALE_FRAMES.py
Time_Frequency_Analysis/STFT_custom.py
Time_Frequency_Analysis/__init__.py
Time_Frequency_Analysis/__main__.py
Time_Frequency_Analysis/cli.py
Time_Frequency_Analysis-0.0.3.dist-info/AUTHORS.rst
Time_Frequency_Analysis-0.0.3.dist-info/LICENSE
Time_Frequency_Analysis-0.0.3.dist-info/METADATA
Time_Frequency_Analysis-0.0.3.dist-info/WHEEL
Time_Frequency_Analysis-0.0.3.dist-info/entry_points.txt
Time_Frequency_Analysis-0.0.3.dist-info/top_level.txt
Time_Frequency_Analysis-0.0.3.dist-info/RECORD
